QuantileClient/__init__.py
QuantileClient/main.py
QuantileClient-0.2.dist-info/METADATA
QuantileClient-0.2.dist-info/WHEEL
QuantileClient-0.2.dist-info/top_level.txt
QuantileClient-0.2.dist-info/RECORD
