Metadata-Version: 2.1
Name: QuantileClient
Version: 0.2
Summary: Its a wrapper lib from quantile ai api service
Home-page: https://github.com/Quantileaidev/QuantileClientLib
Author: QuantileaiDev
Author-email: quantileai@gmail.com
License: MIT
Requires-Dist: python-dotenv
Requires-Dist: requests
